libaaron/__init__.py
libaaron/aio.py
libaaron/libaaron.py
libaaron/py.typed
libaaron/thunks.py
libaaron-1.4.5.dist-info/LICENSE
libaaron-1.4.5.dist-info/WHEEL
libaaron-1.4.5.dist-info/METADATA
libaaron-1.4.5.dist-info/RECORD
