Metadata-Version: 2.1
Name: libaaron
Version: 1.4.5
Summary: trivial functions I like to pack along for various things
Home-page: https://github.com/ninjaaron/libaaron
License: BSD-2-Clause
Author: Aaron Christianson
Author-email: ninjaaron@gmail.com
Requires-Python: >=3.5,<4.0
Classifier: License :: OSI Approved :: BSD License
Classifier: Programming Language :: Python :: 3
Classifier: Programming Language :: Python :: 3.5
Classifier: Programming Language :: Python :: 3.6
Classifier: Programming Language :: Python :: 3.7
Classifier: Programming Language :: Python :: 3.8
Classifier: Programming Language :: Python :: 3.9
Project-URL: Repository, https://github.com/ninjaaron/libaaron
